{"backdrop_path":null,"created_by":[{"id":1213405,"credit_id":"52533b3e19c295794006d6c3","name":"Reg Smythe","profile_path":null}],"episode_run_time":[30],"first_air_date":"1988-02-22","genres":[{"id":35,"name":"Comedy"}],"homepage":"","id":120,"in_production":true,"languages":["en"],"last_air_date":"1988-03-28","last_episode_to_air":{"air_date":"1988-03-28","episode_number":6,"id":5656,"name":"The Anniversary Waltz","overview":"","production_code":"","season_number":1,"show_id":120,"still_path":null,"vote_average":0.0,"vote_count":0},"name":"Andy Capp","next_episode_to_air":null,"networks":[{"name":"ITV","id":9,"logo_path":"/5Rmw4ViYcjW14PCdOyjsue9eK99.png","origin_country":"GB"}],"number_of_episodes":6,"number_of_seasons":1,"origin_country":["GB"],"original_language":"en","original_name":"Andy Capp","overview":"Andy Capp is a British sitcom based on the cartoon Andy Capp. It starred James Bolam and ran for one series in 1988. It was written by Keith Waterhouse. Unusually, for a sitcom, there was no studio audience during the filming of Andy Capp. It was made for the ITV network by Thames Television.","popularity":1.381,"poster_path":null,"production_companies":[],"seasons":[{"air_date":"1988-02-22","episode_count":6,"id":354,"name":"Season 1","overview":"","poster_path":null,"season_number":1}],"status":"Ended","type":"Scripted","vote_average":1.0,"vote_count":1}