{"backdrop_path":null,"created_by":[{"id":1211893,"credit_id":"52534c2319c29579400f93a8","name":"Mark Goodson","gender":0,"profile_path":"/rdXYxS6wMggkgkMo6JZlVX1NnNf.jpg"},{"id":1215279,"credit_id":"52534c2319c29579400f93a2","name":"Bill Todman","gender":0,"profile_path":null}],"episode_run_time":[30],"first_air_date":null,"genres":[],"homepage":"","id":297,"in_production":true,"languages":["en"],"last_air_date":null,"last_episode_to_air":null,"name":"Get the Message","next_episode_to_air":null,"networks":[{"name":"ABC","id":2,"logo_path":"/ndAvF4JLsliGreX87jAc9GdjmJY.png","origin_country":"US"}],"number_of_episodes":0,"number_of_seasons":0,"origin_country":["US"],"original_language":"en","original_name":"Get the Message","overview":"Get the Message was a television game show produced by Mark Goodson and Bill Todman. It aired on ABC's daytime schedule for nine months in 1964, with its last airing on Christmas Day.\n\nThe show was first hosted by Frank Buxton, who was replaced by Robert Q. Lewis on September 28. The announcers were Chet Gould and Johnny Olson.","popularity":0.6,"poster_path":null,"production_companies":[],"seasons":[],"status":"Ended","type":"Scripted","vote_average":0.0,"vote_count":0}