{"backdrop_path":null,"created_by":[{"id":1214962,"credit_id":"525349a419c29579400eac3f","name":"Sharat Sardana","profile_path":null}],"episode_run_time":[30],"first_air_date":"2001-11-12","genres":[{"id":35,"name":"Comedy"}],"homepage":"http://www.bbc.co.uk/comedy/guide/articles/k/kumarsatno42the_66602080.shtml","id":259,"in_production":false,"languages":["en"],"last_air_date":"2006-08-18","last_episode_to_air":{"air_date":"2006-08-18","episode_number":6,"id":14207,"name":"Chris Tarrant and Alan Alda","overview":"","production_code":"","season_number":7,"show_id":259,"still_path":null,"vote_average":0.0,"vote_count":0},"name":"The Kumars at No. 42","next_episode_to_air":null,"networks":[{"name":"BBC One","id":4,"logo_path":"/mVn7xESaTNmjBUyUtGNvDQd3CT1.png","origin_country":"GB"},{"name":"BBC Two","id":332,"logo_path":"/bfAVKGrJGcKTAndYktB7cf8UlBO.png","origin_country":"GB"}],"number_of_episodes":51,"number_of_seasons":7,"origin_country":["GB"],"original_language":"en","original_name":"The Kumars at No. 42","overview":"The Kumars at No. 42 is a British comedy show. It won an International Emmy in 2002 and 2003. It ran for seven series totalling 53 episodes.","popularity":1.91,"poster_path":"/he32P09m0EOa1vYaHYvpSRCqLkZ.jpg","production_companies":[{"id":18939,"logo_path":"/9nn3qLPVfbQJsAmH9ccebkp3fyN.png","name":"Hat Trick Productions","origin_country":"GB"}],"seasons":[{"air_date":null,"episode_count":8,"id":832,"name":"Specials","overview":"","poster_path":null,"season_number":0},{"air_date":"2001-11-12","episode_count":7,"id":826,"name":"Series 1","overview":"","poster_path":null,"season_number":1},{"air_date":"2002-05-27","episode_count":11,"id":825,"name":"Series 2","overview":"","poster_path":null,"season_number":2},{"air_date":"2003-01-06","episode_count":9,"id":827,"name":"Series 3","overview":"","poster_path":null,"season_number":3},{"air_date":"2003-09-15","episode_count":8,"id":828,"name":"Series 4","overview":"","poster_path":null,"season_number":4},{"air_date":"2004-11-08","episode_count":5,"id":829,"name":"Series 5","overview":"","poster_path":null,"season_number":5},{"air_date":"2005-05-27","episode_count":6,"id":830,"name":"Series 6","overview":"","poster_path":null,"season_number":6},{"air_date":"2006-07-14","episode_count":5,"id":831,"name":"Series 7","overview":"","poster_path":null,"season_number":7}],"status":"Ended","type":"Scripted","vote_average":7.0,"vote_count":2}