{"backdrop_path":null,"created_by":[],"episode_run_time":[50],"first_air_date":null,"genres":[{"id":99,"name":"Documentary"}],"homepage":"http://natgeotv.com/uk/making-history","id":105496,"in_production":false,"languages":["en"],"last_air_date":null,"last_episode_to_air":null,"name":"National Geographic Making History","next_episode_to_air":null,"networks":[],"number_of_episodes":3,"number_of_seasons":1,"origin_country":[],"original_language":"en","original_name":"National Geographic Making History","overview":"","popularity":0.6,"poster_path":null,"production_companies":[],"seasons":[{"air_date":null,"episode_count":3,"id":155152,"name":"Season 1","overview":"","poster_path":null,"season_number":1}],"status":"Ended","type":"Documentary","vote_average":0.0,"vote_count":0}